asekuro/__init__.py
asekuro/cli.py
asekuro/common.py
asekuro-0.1.2.dist-info/LICENSE
asekuro-0.1.2.dist-info/METADATA
asekuro-0.1.2.dist-info/WHEEL
asekuro-0.1.2.dist-info/entry_points.txt
asekuro-0.1.2.dist-info/top_level.txt
asekuro-0.1.2.dist-info/RECORD
