Metadata-Version: 2.1
Name: asekuro
Version: 0.1.2
Summary: CLI util to deal with Jupyter Notebooks
Home-page: https://github.com/godatadriven/asekuro
Author: Vincent D. Warmerdam
License: MIT License
Platform: UNKNOWN
Classifier: Topic :: Software Development :: Build Tools
Classifier: Topic :: Utilities
Classifier: Framework :: Jupyter
Classifier: Intended Audience :: Developers
Classifier: Intended Audience :: Science/Research
Classifier: Programming Language :: Python :: 3.6
Classifier: Development Status :: 3 - Alpha
Classifier: License :: OSI Approved :: MIT License
Requires-Python: >=3.6
Requires-Dist: pytest (>=4.0.2)
Requires-Dist: nbval (>=0.9.1)
Requires-Dist: nbformat (>=4.4.0)
Requires-Dist: nbconvert (>=5.4.0)
Requires-Dist: Click (>=7.0)
